setup.py
tomd.py
tomd.egg-info/PKG-INFO
tomd.egg-info/SOURCES.txt
tomd.egg-info/dependency_links.txt
tomd.egg-info/not-zip-safe
tomd.egg-info/top_level.txt