Metadata-Version: 1.1
Name: tomd
Version: 0.1.1
Summary: Convert HTML to Markdown.
Home-page: https://github.com/gaojiuli/tomd
Author: Gaojiuli
Author-email: gaojiuli@aaronsw.com
License: GNU GPL 3
Platform: UNKNOWN
Classifier: Development Status :: 5 - Production/Stable
Classifier: Intended Audience :: Developers
Classifier: License :: OSI Approved :: GNU General Public License (GPL)
Classifier: Programming Language :: Python :: 2.7
Classifier: Programming Language :: Python :: 3.5
